scrape_schema_recipe/VERSION
scrape_schema_recipe/__init__.py
scrape_schema_recipe/example_output.py
scrape_schema_recipe/scrape.py
scrape_schema_recipe/test_data/__init__.py
scrape_schema_recipe/test_data/allrecipes-moscow-mule-2021.html
scrape_schema_recipe/test_data/allrecipes-moscow-mule-2023.html
scrape_schema_recipe/test_data/bevvy-irish-coffee-2018.html
scrape_schema_recipe/test_data/bevvy-irish-coffee-2019.html
scrape_schema_recipe/test_data/crumb-lemon-tea-cakes-2018.html
scrape_schema_recipe/test_data/crumb-lemon-tea-cakes-2019.html
scrape_schema_recipe/test_data/flavorful-green-beans.html
scrape_schema_recipe/test_data/foodista-british-treacle-tart.html
scrape_schema_recipe/test_data/google-recipe-example.html
scrape_schema_recipe/test_data/histfriendly-carrot-fennel-soup.html
scrape_schema_recipe/test_data/mm-skinny-chicken-taco-salad.html
scrape_schema_recipe/test_data/sally-coconut-cake.html
scrape_schema_recipe/test_data/sweetestkitchen-truffles.html
scrape_schema_recipe-0.2.2.dist-info/LICENSE
scrape_schema_recipe-0.2.2.dist-info/METADATA
scrape_schema_recipe-0.2.2.dist-info/WHEEL
scrape_schema_recipe-0.2.2.dist-info/top_level.txt
scrape_schema_recipe-0.2.2.dist-info/zip-safe
scrape_schema_recipe-0.2.2.dist-info/RECORD
