Metadata-Version: 2.1
Name: scrape-schema-recipe
Version: 0.2.2
Summary: Extracts cooking recipe from HTML structured data in the https://schema.org/Recipe format.
Home-page: https://github.com/micahcochran/scrape-schema-recipe
Author: Micah Cochran
License: Apache-2
Keywords: recipe,cooking,food,schema.org,schema.org/Recipe
Classifier: Intended Audience :: Developers
Classifier: Operating System :: OS Independent
Classifier: License :: OSI Approved :: Apache Software License
Classifier: Programming Language :: Python :: 3
Classifier: Topic :: Internet :: WWW/HTTP
Classifier: Topic :: Text Processing :: Markup :: HTML
License-File: LICENSE
Requires-Dist: setuptools>=39.2.0
Requires-Dist: dataclasses; python_version < "3.7"
Requires-Dist: extruct
Requires-Dist: importlib_resources; python_version < "3.9"
Requires-Dist: isodate>=0.5.1
Requires-Dist: requests
Requires-Dist: types-dataclasses; python_version < "3.7"
